setup.py
oink/__init__.py
oink/cli.py
oink.egg-info/PKG-INFO
oink.egg-info/SOURCES.txt
oink.egg-info/dependency_links.txt
oink.egg-info/entry_points.txt
oink.egg-info/not-zip-safe
oink.egg-info/top_level.txt