Metadata-Version: 1.0
Name: oink
Version: 0.1.0
Summary: A CLI budgeting tools for nerds.
Home-page: http://github.com/geekforbrains/oink
Author: Gavin Vickery
Author-email: gavin@geekforbrains.com
License: MIT
Platform: UNKNOWN
